getpass3/getpass3.py
getpass3-1.2.dist-info/DESCRIPTION.rst
getpass3-1.2.dist-info/METADATA
getpass3-1.2.dist-info/RECORD
getpass3-1.2.dist-info/WHEEL
getpass3-1.2.dist-info/metadata.json
getpass3-1.2.dist-info/top_level.txt
