Metadata-Version: 2.0
Name: getpass3
Version: 1.2
Summary: The getpass3 is similar like getpass except it encrypts the echo of what you write in the terminal and display it.
Home-page: https://github.com/J16N/getpass3
Author: Jishan Bhattacharya
Author-email: scientistjishan@gmail.com
License: UNKNOWN
Download-URL: https://github.com/J16N/getpass3/archive/1.0.tar.gz
Keywords: testing,password,echoing,encryption
Platform: UNKNOWN
